JSON_messenger_server-0.1a2.data/scripts/server.py
jim/__init__.py
jim/classes.py
jim/config.py
jim/decorators.py
jim/descriptors.py
jim/exceptions.py
jim/logger.py
jim/messages.py
jim/metaclasses.py
jim/models.py
jim/security.py
jim/utils.py
tests/__init__.py
tests/test_decorators.py
tests/test_logger.py
tests/test_messages.py
tests/test_utils.py
ui/__init__.py
ui/historyDialog.py
ui/mainWindow.py
ui/settingsDialog.py
JSON_messenger_server-0.1a2.dist-info/METADATA
JSON_messenger_server-0.1a2.dist-info/WHEEL
JSON_messenger_server-0.1a2.dist-info/top_level.txt
JSON_messenger_server-0.1a2.dist-info/RECORD
